Workbook

Sheet Dépenses
A1: Comptabilité Salverys — registre des coûts
A2: Une ligne = un coût. Périodicité Mensuel/Annuel/Ponctuel · Statut Payé/À payer · taux Ar dans la feuille Paramètres.
A4: Fournisseur / Outil | B4: Catégorie | C4: Description | D4: Périodicité | E4: Montant (€) | F4: Équiv. mensuel (€) | G4: Équivalent (Ar) | H4: Compte / email utilisé | I4: Statut | J4: Prochaine échéance | K4: Date de paiement | L4: Moyen de paiement | M4: Notes
A5: Emelia | B5: Marketing | C5: Cold mailing — plan avec warm-up auto | D5: Mensuel | E5: 99 | F5: =IF(OR($E5="",$D5=""),"",IF($D5="Mensuel",$E5,IF($D5="Annuel",$E5/12,""))) | G5: =IF($E5="","",$E5*'Paramètres'!$B$3) | I5: À payer | L5: CB | M5: Outil outreach retenu
A6: CloudTalk | B6: Téléphonie | C6: Essential — numéro +33, par utilisateur | D6: Mensuel | E6: 29 | F6: =IF(OR($E6="",$D6=""),"",IF($D6="Mensuel",$E6,IF($D6="Annuel",$E6/12,""))) | G6: =IF($E6="","",$E6*'Paramètres'!$B$3) | I6: À payer | L6: CB | M6: × nb d'utilisateurs (méd.)
A7: Microsoft 365 | B7: SaaS & outils | C7: Business Basic + Teams (salverys.fr) | D7: Mensuel | E7: 6 | F7: =IF(OR($E7="",$D7=""),"",IF($D7="Mensuel",$E7,IF($D7="Annuel",$E7/12,""))) | G7: =IF($E7="","",$E7*'Paramètres'!$B$3) | I7: À payer | L7: CB | M7: par licence
A8: Google Workspace | B8: SaaS & outils | C8: Licence mailing (inbox cold email) | D8: Mensuel | E8: 10 | F8: =IF(OR($E8="",$D8=""),"",IF($D8="Mensuel",$E8,IF($D8="Annuel",$E8/12,""))) | G8: =IF($E8="","",$E8*'Paramètres'!$B$3) | I8: À payer | L8: CB | M8: par licence
A9: OVH | B9: Domaines & hébergement | C9: Domaine salverys.fr + sous-domaines | D9: Annuel | E9: 12 | F9: =IF(OR($E9="",$D9=""),"",IF($D9="Mensuel",$E9,IF($D9="Annuel",$E9/12,""))) | G9: =IF($E9="","",$E9*'Paramètres'!$B$3) | I9: À payer | L9: CB | M9: ≈ 1 €/mois
A10: OVH | B10: Domaines & hébergement | C10: Domaine cold email salverys-bpo.fr | D10: Annuel | E10: 12 | F10: =IF(OR($E10="",$D10=""),"",IF($D10="Mensuel",$E10,IF($D10="Annuel",$E10/12,""))) | G10: =IF($E10="","",$E10*'Paramètres'!$B$3) | I10: À payer | L10: CB | M10: domaine isolé outreach
A11: HubSpot | B11: SaaS & outils | C11: CRM commercial — plan Free | D11: Mensuel | E11: 0 | F11: =IF(OR($E11="",$D11=""),"",IF($D11="Mensuel",$E11,IF($D11="Annuel",$E11/12,""))) | G11: =IF($E11="","",$E11*'Paramètres'!$B$3) | I11: Payé | L11: Autre | M11: 0 € — décision tranchée
A12: Netlify | B12: Domaines & hébergement | C12: Hébergement site — plan Free | D12: Mensuel | E12: 0 | F12: =IF(OR($E12="",$D12=""),"",IF($D12="Mensuel",$E12,IF($D12="Annuel",$E12/12,""))) | G12: =IF($E12="","",$E12*'Paramètres'!$B$3) | I12: Payé | L12: Autre
A13: GitHub | B13: SaaS & outils | C13: Repo Salve2 — plan Free | D13: Mensuel | E13: 0 | F13: =IF(OR($E13="",$D13=""),"",IF($D13="Mensuel",$E13,IF($D13="Annuel",$E13/12,""))) | G13: =IF($E13="","",$E13*'Paramètres'!$B$3) | I13: Payé | L13: Autre
A14: Anthropic / Claude | B14: SaaS & outils | C14: Abonnement Claude (dev & assets) | D14: Mensuel | F14: =IF(OR($E14="",$D14=""),"",IF($D14="Mensuel",$E14,IF($D14="Annuel",$E14/12,""))) | G14: =IF($E14="","",$E14*'Paramètres'!$B$3) | I14: À payer | L14: CB | M14: montant selon plan
A15: Freelance agent | B15: Salaires freelances | C15: Agent (3 250 000 Ar ≈ 650 €) | D15: Mensuel | E15: 650 | F15: =IF(OR($E15="",$D15=""),"",IF($D15="Mensuel",$E15,IF($D15="Annuel",$E15/12,""))) | G15: =IF($E15="","",$E15*'Paramètres'!$B$3) | I15: À payer | L15: Wise | M15: 1 ligne par agent
A16: Freelance manager | B16: Salaires freelances | C16: Manager méd. ou IT (3 250 000 Ar) | D16: Mensuel | E16: 650 | F16: =IF(OR($E16="",$D16=""),"",IF($D16="Mensuel",$E16,IF($D16="Annuel",$E16/12,""))) | G16: =IF($E16="","",$E16*'Paramètres'!$B$3) | I16: À payer | L16: Wise | M16: 1 ligne par manager
A17: Wise Business | B17: Banque & frais | C17: Frais de change / virement EUR→MGA | D17: Mensuel | F17: =IF(OR($E17="",$D17=""),"",IF($D17="Mensuel",$E17,IF($D17="Annuel",$E17/12,""))) | G17: =IF($E17="","",$E17*'Paramètres'!$B$3) | I17: À payer | L17: Wise | M17: variable selon volumes
A18: VJUS | B18: Administratif & légal | C18: Création société malgache (setup) | D18: Ponctuel | F18: =IF(OR($E18="",$D18=""),"",IF($D18="Mensuel",$E18,IF($D18="Annuel",$E18/12,""))) | G18: =IF($E18="","",$E18*'Paramètres'!$B$3) | I18: À payer | L18: Virement | M18: formalités
F19: =IF(OR($E19="",$D19=""),"",IF($D19="Mensuel",$E19,IF($D19="Annuel",$E19/12,""))) | G19: =IF($E19="","",$E19*'Paramètres'!$B$3)
F20: =IF(OR($E20="",$D20=""),"",IF($D20="Mensuel",$E20,IF($D20="Annuel",$E20/12,""))) | G20: =IF($E20="","",$E20*'Paramètres'!$B$3)
F21: =IF(OR($E21="",$D21=""),"",IF($D21="Mensuel",$E21,IF($D21="Annuel",$E21/12,""))) | G21: =IF($E21="","",$E21*'Paramètres'!$B$3)
F22: =IF(OR($E22="",$D22=""),"",IF($D22="Mensuel",$E22,IF($D22="Annuel",$E22/12,""))) | G22: =IF($E22="","",$E22*'Paramètres'!$B$3)
F23: =IF(OR($E23="",$D23=""),"",IF($D23="Mensuel",$E23,IF($D23="Annuel",$E23/12,""))) | G23: =IF($E23="","",$E23*'Paramètres'!$B$3)
F24: =IF(OR($E24="",$D24=""),"",IF($D24="Mensuel",$E24,IF($D24="Annuel",$E24/12,""))) | G24: =IF($E24="","",$E24*'Paramètres'!$B$3)
F25: =IF(OR($E25="",$D25=""),"",IF($D25="Mensuel",$E25,IF($D25="Annuel",$E25/12,""))) | G25: =IF($E25="","",$E25*'Paramètres'!$B$3)
F26: =IF(OR($E26="",$D26=""),"",IF($D26="Mensuel",$E26,IF($D26="Annuel",$E26/12,""))) | G26: =IF($E26="","",$E26*'Paramètres'!$B$3)
F27: =IF(OR($E27="",$D27=""),"",IF($D27="Mensuel",$E27,IF($D27="Annuel",$E27/12,""))) | G27: =IF($E27="","",$E27*'Paramètres'!$B$3)
F28: =IF(OR($E28="",$D28=""),"",IF($D28="Mensuel",$E28,IF($D28="Annuel",$E28/12,""))) | G28: =IF($E28="","",$E28*'Paramètres'!$B$3)
F29: =IF(OR($E29="",$D29=""),"",IF($D29="Mensuel",$E29,IF($D29="Annuel",$E29/12,""))) | G29: =IF($E29="","",$E29*'Paramètres'!$B$3)
F30: =IF(OR($E30="",$D30=""),"",IF($D30="Mensuel",$E30,IF($D30="Annuel",$E30/12,""))) | G30: =IF($E30="","",$E30*'Paramètres'!$B$3)
... F124: =IF(OR($E124="",$D124=""),"",IF($D124="Mensuel",$E124,IF($D124="Annuel",$E124/12,""))) | G124: =IF($E124="","",$E124*'Paramètres'!$B$3)

Sheet Récap
A1: Récapitulatif
A2: Se met à jour automatiquement depuis la feuille Dépenses.
A4: Total récurrent mensuel (€) | B4: =SUM(Dépenses!$F$5:$F$124)
A5: Total récurrent mensuel (Ar) | B5: =SUM(Dépenses!$F$5:$F$124)*'Paramètres'!$B$3
A6: Total annuel projeté (€) | B6: =SUM(Dépenses!$F$5:$F$124)*12
A8: Total « À payer » (€) | B8: =SUMIF(Dépenses!$I$5:$I$124,"À payer",Dépenses!$E$5:$E$124)
A9: Total « Payé » (€) | B9: =SUMIF(Dépenses!$I$5:$I$124,"Payé",Dépenses!$E$5:$E$124)
A11: Dépenses ponctuelles (€) | B11: =SUMIF(Dépenses!$D$5:$D$124,"Ponctuel",Dépenses!$E$5:$E$124)
A13: Récurrent mensuel par catégorie | B13: € / mois
A14: SaaS & outils | B14: =SUMIF(Dépenses!$B$5:$B$124,$A14,Dépenses!$F$5:$F$124)
A15: Salaires freelances | B15: =SUMIF(Dépenses!$B$5:$B$124,$A15,Dépenses!$F$5:$F$124)
A16: Téléphonie | B16: =SUMIF(Dépenses!$B$5:$B$124,$A16,Dépenses!$F$5:$F$124)
A17: Domaines & hébergement | B17: =SUMIF(Dépenses!$B$5:$B$124,$A17,Dépenses!$F$5:$F$124)
A18: Administratif & légal | B18: =SUMIF(Dépenses!$B$5:$B$124,$A18,Dépenses!$F$5:$F$124)
A19: Banque & frais | B19: =SUMIF(Dépenses!$B$5:$B$124,$A19,Dépenses!$F$5:$F$124)
A20: Marketing | B20: =SUMIF(Dépenses!$B$5:$B$124,$A20,Dépenses!$F$5:$F$124)
A21: Autre | B21: =SUMIF(Dépenses!$B$5:$B$124,$A21,Dépenses!$F$5:$F$124)
A22: Total | B22: =SUM(B14:B21)

Sheet Paramètres
A1: Paramètres
A3: Taux EUR → MGA (Ar / €) | B3: 5000
A4: Modifier ce taux met à jour la colonne « Équivalent (Ar) » de la feuille Dépenses.
A6: Catégories | B6: Périodicités | C6: Statuts | D6: Moyens de paiement
A7: SaaS & outils | B7: Mensuel | C7: Payé | D7: Wise
A8: Salaires freelances | B8: Annuel | C8: À payer | D8: CB
A9: Téléphonie | B9: Ponctuel | D9: Virement
A10: Domaines & hébergement | D10: Mobile money
A11: Administratif & légal | D11: Autre
A12: Banque & frais
A13: Marketing
A14: Autre
