Workbook

Sheet Synthèse
C1: Projection de finances Salverys
C2: Prévision, pas situation bancaire. Chaque cellule calculée est une formule vivante.
A5: Indicateur | B5: Valeur | C5: Lecture
A6: Creux de trésorerie | B6: =MIN(Flux!L6:L29) -> -16948 | C6: Le plus bas du cash sur l'horizon. C'est le montant à financer si la trésorerie de départ est nulle.
A7: Mois du creux | B7: =INDEX(Flux!A6:A29,MATCH(MIN(Flux!L6:L29),Flux!L6:L29,0)) -> 6 | C7: Quand il tombe.
A8: Besoin illustratif, creux + 30 % | B8: =MAX(0,-MIN(Flux!L6:L29))*1.3 -> 22032.4 | C8: Coussin arbitraire de 30 %. Hors dettes et coûts non renseignés. PAS une recommandation de capital.
A9: Trésorerie à M24 | B9: =Flux!L29 -> 50768 | C9: Fin de l'horizon, si aucun nouveau contrat n'est signé après ceux de l'onglet Contrats.
A10: Résultat mensuel à régime plein | B10: =Contribution!E20 -> 3762 | C10: Tous contrats actifs, structure et réserves comprises, hors onboarding, équipement, impayés et taxes.
A11: Agents à régime plein | B11: =Flux!B29 -> 5
A12: Managers à régime plein | B12: =Flux!C29 -> 0 | C12: Un par tranche de 8 positions, dans chaque métier. La supervision n'est pas mutualisée entre métiers.
A13: Coût d'une position | B13: =Hypothèses!B14 -> 730 | C13: Coût complet agent tout compris + VoIP (arbitrage A7, à valider par la paie).
A14: Prix minimal viable par position | B14: =Grille!B13 -> 856.96392 | C14: En dessous, aucun volume ne rattrape le prix. Structure du lancement non comprise.
A16: CE QUE CE CLASSEUR NE CONTIENT PAS
A17: Impôts et TVA, assurance, amortissements comptables, recrutement au-delà du forfait d'onboarding, indemnités de rupture, dettes et créances existantes, dates réelles des factures annuelles. Le modèle A mutualisé (1 120 € / 400 tickets) et le télésecrétariat médical facturé à l'appel ne sont pas projetés : leur staffing n'est pas mesuré.
A19: COMMENT S'EN SERVIR
A20: Onglet Hypothèses : les cellules bleues pilotent tout le classeur. Onglet Contrats : une ligne par contrat, huit au maximum. Les onglets Flux, Contribution et Synthèse sont entièrement calculés — n'y écrivez pas. Ce classeur est généré par tools/export-xlsx.py depuis tools/finance-model.mjs : le régénérer écrase vos saisies, alors travaillez sur une copie.
A22: OÙ EST LA VÉRITÉ
A23: PRICING.md fait foi sur les prix. AUDIT-CHIFFRES-2026-09-18.md dit, pour chaque chiffre du dépôt, s'il est vérifié, hypothétique, estimé ou faux aujourd'hui. projection-finances-salverys.html est la version interactive de ce classeur ; grille-negociation-salverys.html dit à quel prix signer. Les trois partagent le moteur tools/finance-model.mjs.

Sheet Hypothèses
C1: Hypothèses
C2: Cellules bleues : à modifier. Tout le classeur en dépend. Noir : calculé.
A4: Paramètre | B4: Valeur | C4: Unité | D4: Statut et source
A5: PERSONNEL
A6: Brut mensuel manager (et agent si B39 = 0) | B6: 3250000 | C6: Ar | D6: Décision direction 2026-08-14. À confirmer sur bulletins de paie. Depuis le 2026-09-24, l'agent se chiffre au coût complet de la ligne 39.
A7: Taux de change | B7: 5000 | C7: Ar / € | D7: Convention de simulation. Remplacer par le taux de paiement réel et ses frais.
A8: Cotisations employeur | B8: 0.18 | C8: % du brut | D8: HYPOTHÈSE RÉGLEMENTAIRE NON VÉRIFIÉE. À confirmer auprès du gestionnaire de paie.
A9: SME retenu | B9: 300000 | C9: Ar | D9: lexpress.mg, février 2026. Sert au plafond de cotisation.
A10: Plafond de cotisation (8 × SME) | B10: =B9*8 -> 2400000 | C10: Ar | D10: Calculé.
A11: VoIP par agent | B11: 30 | C11: € / mois | D11: Devis ou facture à obtenir.
A12: VoIP par manager | B12: 0 | C12: € / mois | D12: Hypothèse : le manager n'a pas de ligne facturée. À corriger s'il décroche.
A13: Coussin sur personnel | B13: 0.1 | C13: % | D13: Réserve prudente, retirée du cash. Ce n'est pas une paie versée.
A14: Coût d'un agent | B14: =IF(B39>0,B39/B7+B11,((B6+MIN(B6,B10)*B8)/B7+B11)*(1+B13)) -> 730 | C14: € / mois | D14: Calculé : coût complet (ligne 39) ÷ change + VoIP, sans coussin. Si la ligne 39 vaut 0 : (brut + cotisations plafonnées) ÷ change, plus VoIP, plus coussin.
A15: Coût d'un manager | B15: =((B6+MIN(B6,B10)*B8)/B7+B12)*(1+B13) -> 810.04 | C15: € / mois | D15: Calculé, même formule sans la VoIP agent.
A16: Positions par manager | B16: 8 | C16: positions | D16: Un manager de plus par tranche, DANS CHAQUE MÉTIER.
A17: Positions encadrées par le fondateur | B17: 5 | C17: positions | D17: Arbitrage A10 du 2026-09-24 : le fondateur encadre le lancement à 5 positions. Un manager s'ajoute à la 6e ; le forfait d'encadrement de la ligne 40 est alors à recalculer.
A18: STRUCTURE ET DÉMARRAGE
A19: Outils récurrents connus | B19: 68 | C19: € / mois | D19: REGISTRE-COUTS-OUTILS.md : 65 € d'abonnements + 36 €/an de domaines. Montants DÉCLARÉS, non rapprochés de factures.
A20: Charges mensuelles supplémentaires | B20: 0 | C20: € / mois | D20: À REMPLIR : taxes, comptabilité, assurance, frais bancaires, équipement, congés. Laisser 0 est une décision.
A21: Onboarding — socle par contrat | B21: 400 | C21: € | D21: AUDIT-ESPACE-CLIENT.md §9.2. Ordre de grandeur non documenté sur temps passé.
A22: Onboarding — par position | B22: 400 | C22: € | D22: Idem. Le forfait de 1 600 €/contrat utilisé jusqu'au 2026-09-16 ne valait que pour 3 positions.
A23: Embauche après signature | B23: 1 | C23: mois | D23: C'est ce délai qui crée le creux : la paie part avant la première facture.
A24: Première facture après signature | B24: 2 | C24: mois | D24: Hypothèse. Le devis date le début de facturation, et c'est lui qui fait foi.
A25: ENCAISSEMENT ET RISQUE
A26: Règlement après facture | B26: 1 | C26: mois | D26: PRICING.md §3 : paiement à 30 jours. Paramètre le plus sensible du modèle.
A27: Dépôt par position | B27: 0 | C27: € | D27: SUPPRIMÉ de la grille le 2026-09-24 (arbitrage A1), remplacé par les frais de mise en service. Gardé pour simuler l'ancien dépôt rendu par crédit de facture.
A28: Crédit de dépôt par facture | B28: 0 | C28: € | D28: Ancien mécanisme, à 0.
A29: Factures créditées | B29: 3 | C29: nb | D29: Ancien mécanisme.
A30: Résidu de dépôt NON rendu | B30: =B27-B28*B29 -> 0 | C30: € / position | D30: Doit valoir 0. Positif = frais d'activation déguisé, à nommer. Négatif = argent jamais encaissé, offert.
A31: Frais de mise en service par contrat | B31: 0 | C31: € | D31: Part fixe éventuelle. PRICING.md §3 n'en prévoit pas.
A32: Frais de mise en service par position | B32: 490 | C32: € | D32: PRICING.md §3, arbitrage A1 du 2026-09-24 : 490 €/position à la signature, acquis, non imputés sur les mensualités.
A33: Impayés sur CA encaissé | B33: 0 | C33: % | D33: 0 % n'est pas une mesure, c'est une absence d'historique.
A34: Banque, change et taxes sur CA encaissé | B34: 0.01 | C34: % | D34: Arbitrage A9 : 1 % de frais bancaires et risque de change. Taxes non comprises : taux non vérifiés.
A35: DÉPART
A36: Trésorerie de départ | B36: 0 | C36: € | D36: 0 mesure un BESOIN THÉORIQUE. Ce n'est pas le solde réel de Salverys.
A38: ARBITRAGES DU 2026-09-24 (BMC v1.3)
A39: Coût complet agent, tout compris | B39: 3500000 | C39: Ar / mois | D39: Arbitrage A7 : rémunération, charges, congés, absences, formation et remplacement. À VALIDER PAR LA PAIE : le brut de la ligne 6 chargé n'y tient pas. 0 = calcul par le brut.
A40: Structure dès la 1re embauche | B40: 2220 | C40: € / mois | D40: Arbitrage A8, hypothèse pessimiste : encadrement / QA 600 + loyer 60 m² 720 + double fibre 300 + RH / paie / comptable 300 + énergie 300. Payée tant qu'un agent est en poste.
A41: Poste de travail par position | B41: 800 | C41: € | D41: Laptop + écran, 4 M Ar, décaissés à la signature.
A42: Groupe électrogène + UPS | B42: 450 | C42: € | D42: 2,25 M Ar, décaissés une fois, au premier mois avec du personnel. À tester avant d'être promis.
A43: Provision avoirs SLA sur CA encaissé | B43: 0.02 | C43: % | D43: Arbitrage A9 : avoir de 20 % au plus un mois sur douze = 1,7 % du CA ; provision de 2 %.
A45: Aucun chiffre de ce classeur ne représente une dépense constatée tant que les factures, la paie et le solde bancaire n'ont pas été rapprochés. Trois hypothèses pèsent sur tout le reste : le taux de cotisation, le plafond et le taux de change. Elles fixent le coût d'une position, donc toute marge annoncée.

Sheet Grille
C1: Grille tarifaire
C2: PRICING.md §1 fait foi. Tranches NON rétroactives depuis le 2026-09-18.
A4: Positions facturées au tarif d'entrée
A5: Tranche d'entrée | B5: 4 | C5: positions
A7: Métier | B7: Tarif d'entrée | C7: Tarif volume | D7: Commentaire
A8: helpdesk | B8: 2000 | C8: 1750 | D8: Positions 1 à 4 au tarif d'entrée, 5 et suivantes au tarif volume. La remise ne s'applique jamais aux positions déjà tarifées.
A9: support | B9: 1700 | C9: 1500 | D9: Positions 1 à 4 au tarif d'entrée, 5 et suivantes au tarif volume. La remise ne s'applique jamais aux positions déjà tarifées.
A11: PLANCHERS
A12: Plancher de négociation PRICING.md | B12: 920 | D12: À RÉVISER. Garde-fou de négociation, pas seuil de rentabilité : comparer à la ligne 13, puis chiffrer le contrat avec la structure du lancement.
A13: Prix minimal viable, quel que soit le volume | B13: =(Hypothèses!B14+Hypothèses!B15/Hypothèses!B16)/(1-Hypothèses!B34-Hypothèses!B43) -> 856.96392 | D13: Coût d'un agent plus sa quote-part de manager, réserves sur CA comprises. En dessous, aucun volume ne rattrape le prix. Structure du lancement non comprise.
A15: CLIENT FINAL — AUCUNE GRILLE ARBITRÉE
A16: Repère archivé helpdesk | B16: 2200 | C16: 2800
A17: Repère archivé support | B17: 1900 | C17: 2400
A18: Ces fourchettes viennent du registre interne archivé (évaluation du 2026-06-10). AUCUNE DÉCISION DATÉE NE LES FIXE, et les sources de cette étude sont des sites de télésecrétariat médical et des BPO généralistes — aucune ne publie un prix de position dédiée en IT. Ne pas s'en servir comme tarif : un entrant se chiffre au coût réel et à la marge visée. Détail : AUDIT-CHIFFRES-2026-09-18.md.

Sheet Contrats
C1: Contrats
C2: Cellules bleues : à modifier. Une ligne par contrat, huit au maximum.
A5: Nom | B5: Mois de signature | C5: Métier | D5: Positions fermes | E5: Tarif | F5: Prix libre (€) | G5: CA mensuel | H5: Onboarding | I5: Dépôt encaissé | J5: Mise en service | K5: Crédit de dépôt / facture | L5: Postes de travail
A6: Client A | B6: 4 | C6: helpdesk | D6: 3 | E6: mb | G6: =IF($D6="",0,IF($E6="mb",MIN($D6,Grille!$B$5)*INDEX(Grille!$B$8:$B$9,MATCH($C6,Grille!$A$8:$A$9,0))+MAX(0,$D6-Grille!$B$5)*INDEX(Grille!$C$8:$C$9,MATCH($C6,Grille!$A$8:$A$9,0)),$D6*$F6)) -> 6000 | H6: =IF($D6="",0,Hypothèses!$B$21+$D6*Hypothèses!$B$22) -> 1600 | I6: =IF($D6="",0,$D6*Hypothèses!$B$27) -> 0 | J6: =IF($D6="",0,Hypothèses!$B$31+$D6*Hypothèses!$B$32) -> 1470 | K6: =IF($D6="",0,$D6*Hypothèses!$B$28) -> 0 | L6: =IF($D6="",0,$D6*Hypothèses!$B$41) -> 2400
A7: Client B | B7: 4 | C7: helpdesk | D7: 2 | E7: mb | G7: =IF($D7="",0,IF($E7="mb",MIN($D7,Grille!$B$5)*INDEX(Grille!$B$8:$B$9,MATCH($C7,Grille!$A$8:$A$9,0))+MAX(0,$D7-Grille!$B$5)*INDEX(Grille!$C$8:$C$9,MATCH($C7,Grille!$A$8:$A$9,0)),$D7*$F7)) -> 4000 | H7: =IF($D7="",0,Hypothèses!$B$21+$D7*Hypothèses!$B$22) -> 1200 | I7: =IF($D7="",0,$D7*Hypothèses!$B$27) -> 0 | J7: =IF($D7="",0,Hypothèses!$B$31+$D7*Hypothèses!$B$32) -> 980 | K7: =IF($D7="",0,$D7*Hypothèses!$B$28) -> 0 | L7: =IF($D7="",0,$D7*Hypothèses!$B$41) -> 1600
G8: =IF($D8="",0,IF($E8="mb",MIN($D8,Grille!$B$5)*INDEX(Grille!$B$8:$B$9,MATCH($C8,Grille!$A$8:$A$9,0))+MAX(0,$D8-Grille!$B$5)*INDEX(Grille!$C$8:$C$9,MATCH($C8,Grille!$A$8:$A$9,0)),$D8*$F8)) -> 0 | H8: =IF($D8="",0,Hypothèses!$B$21+$D8*Hypothèses!$B$22) -> 0 | I8: =IF($D8="",0,$D8*Hypothèses!$B$27) -> 0 | J8: =IF($D8="",0,Hypothèses!$B$31+$D8*Hypothèses!$B$32) -> 0 | K8: =IF($D8="",0,$D8*Hypothèses!$B$28) -> 0 | L8: =IF($D8="",0,$D8*Hypothèses!$B$41) -> 0
G9: =IF($D9="",0,IF($E9="mb",MIN($D9,Grille!$B$5)*INDEX(Grille!$B$8:$B$9,MATCH($C9,Grille!$A$8:$A$9,0))+MAX(0,$D9-Grille!$B$5)*INDEX(Grille!$C$8:$C$9,MATCH($C9,Grille!$A$8:$A$9,0)),$D9*$F9)) -> 0 | H9: =IF($D9="",0,Hypothèses!$B$21+$D9*Hypothèses!$B$22) -> 0 | I9: =IF($D9="",0,$D9*Hypothèses!$B$27) -> 0 | J9: =IF($D9="",0,Hypothèses!$B$31+$D9*Hypothèses!$B$32) -> 0 | K9: =IF($D9="",0,$D9*Hypothèses!$B$28) -> 0 | L9: =IF($D9="",0,$D9*Hypothèses!$B$41) -> 0
G10: =IF($D10="",0,IF($E10="mb",MIN($D10,Grille!$B$5)*INDEX(Grille!$B$8:$B$9,MATCH($C10,Grille!$A$8:$A$9,0))+MAX(0,$D10-Grille!$B$5)*INDEX(Grille!$C$8:$C$9,MATCH($C10,Grille!$A$8:$A$9,0)),$D10*$F10)) -> 0 | H10: =IF($D10="",0,Hypothèses!$B$21+$D10*Hypothèses!$B$22) -> 0 | I10: =IF($D10="",0,$D10*Hypothèses!$B$27) -> 0 | J10: =IF($D10="",0,Hypothèses!$B$31+$D10*Hypothèses!$B$32) -> 0 | K10: =IF($D10="",0,$D10*Hypothèses!$B$28) -> 0 | L10: =IF($D10="",0,$D10*Hypothèses!$B$41) -> 0
G11: =IF($D11="",0,IF($E11="mb",MIN($D11,Grille!$B$5)*INDEX(Grille!$B$8:$B$9,MATCH($C11,Grille!$A$8:$A$9,0))+MAX(0,$D11-Grille!$B$5)*INDEX(Grille!$C$8:$C$9,MATCH($C11,Grille!$A$8:$A$9,0)),$D11*$F11)) -> 0 | H11: =IF($D11="",0,Hypothèses!$B$21+$D11*Hypothèses!$B$22) -> 0 | I11: =IF($D11="",0,$D11*Hypothèses!$B$27) -> 0 | J11: =IF($D11="",0,Hypothèses!$B$31+$D11*Hypothèses!$B$32) -> 0 | K11: =IF($D11="",0,$D11*Hypothèses!$B$28) -> 0 | L11: =IF($D11="",0,$D11*Hypothèses!$B$41) -> 0
G12: =IF($D12="",0,IF($E12="mb",MIN($D12,Grille!$B$5)*INDEX(Grille!$B$8:$B$9,MATCH($C12,Grille!$A$8:$A$9,0))+MAX(0,$D12-Grille!$B$5)*INDEX(Grille!$C$8:$C$9,MATCH($C12,Grille!$A$8:$A$9,0)),$D12*$F12)) -> 0 | H12: =IF($D12="",0,Hypothèses!$B$21+$D12*Hypothèses!$B$22) -> 0 | I12: =IF($D12="",0,$D12*Hypothèses!$B$27) -> 0 | J12: =IF($D12="",0,Hypothèses!$B$31+$D12*Hypothèses!$B$32) -> 0 | K12: =IF($D12="",0,$D12*Hypothèses!$B$28) -> 0 | L12: =IF($D12="",0,$D12*Hypothèses!$B$41) -> 0
G13: =IF($D13="",0,IF($E13="mb",MIN($D13,Grille!$B$5)*INDEX(Grille!$B$8:$B$9,MATCH($C13,Grille!$A$8:$A$9,0))+MAX(0,$D13-Grille!$B$5)*INDEX(Grille!$C$8:$C$9,MATCH($C13,Grille!$A$8:$A$9,0)),$D13*$F13)) -> 0 | H13: =IF($D13="",0,Hypothèses!$B$21+$D13*Hypothèses!$B$22) -> 0 | I13: =IF($D13="",0,$D13*Hypothèses!$B$27) -> 0 | J13: =IF($D13="",0,Hypothèses!$B$31+$D13*Hypothèses!$B$32) -> 0 | K13: =IF($D13="",0,$D13*Hypothèses!$B$28) -> 0 | L13: =IF($D13="",0,$D13*Hypothèses!$B$41) -> 0
A15: Métier : helpdesk ou support, en minuscules. Tarif : « mb » applique la grille par tranches de l'onglet Grille ; toute autre valeur applique le prix libre de la colonne F. En client final, le prix est OBLIGATOIREMENT saisi en colonne F : aucune grille directe n'existe. Ligne d'exemple : Partenaire A · 4 · helpdesk · 2 · mb · (vide) → 4 000 € de CA mensuel.

Sheet Flux
C1: Flux mensuels
C2: Tout est formule. Modifiez Hypothèses ou Contrats : ce tableau suit.
A5: Mois | B5: Agents | C5: Mgr | D5: Dépôt | E5: Activation | F5: Facturé | G5: Encaissé | H5: Personnel | I5: Onboarding et équipement | J5: Structure et réserves | K5: Résultat | L5: Cash fin de mois | M5: Positions helpdesk | N5: Positions support
A6: 1 | B6: =$M6+$N6 -> 0 | C6: =IF($B6<=Hypothèses!$B$17,0,IF($M6=0,0,CEILING($M6/Hypothèses!$B$16,1))+IF($N6=0,0,CEILING($N6/Hypothèses!$B$16,1))) -> 0 | D6: =SUMPRODUCT((Contrats!$B$6:$B$13=$A6)*Contrats!$I$6:$I$13) -> 0 | E6: =SUMPRODUCT((Contrats!$B$6:$B$13=$A6)*Contrats!$J$6:$J$13) -> 0 | F6: =SUMPRODUCT(($A6>=Contrats!$B$6:$B$13+Hypothèses!$B$24)*Contrats!$G$6:$G$13)-SUMPRODUCT(($A6-Contrats!$B$6:$B$13-Hypothèses!$B$24>=0)*($A6-Contrats!$B$6:$B$13-Hypothèses!$B$24<Hypothèses!$B$29)*Contrats!$K$6:$K$13) -> 0 | G6: =(SUMPRODUCT(($A6>=Contrats!$B$6:$B$13+Hypothèses!$B$24+Hypothèses!$B$26)*Contrats!$G$6:$G$13)-SUMPRODUCT(($A6-Hypothèses!$B$26-Contrats!$B$6:$B$13-Hypothèses!$B$24>=0)*($A6-Hypothèses!$B$26-Contrats!$B$6:$B$13-Hypothèses!$B$24<Hypothèses!$B$29)*Contrats!$K$6:$K$13))*(1-Hypothèses!$B$33) -> 0 | H6: =-($B6*Hypothèses!$B$14+$C6*Hypothèses!$B$15) -> 0 | I6: =-SUMPRODUCT((Contrats!$B$6:$B$13=$A6)*Contrats!$H$6:$H$13)-SUMPRODUCT((Contrats!$B$6:$B$13=$A6)*Contrats!$L$6:$L$13)-IF(AND($B6>0,COUNTIF($B$6:$B6,">0")=1),Hypothèses!$B$42,0) -> 0 | J6: =-(Hypothèses!$B$19+Hypothèses!$B$20+IF($B6>0,Hypothèses!$B$40,0)+$G6*(Hypothèses!$B$34+Hypothèses!$B$43)) -> -68 | K6: =$G6+$E6+$H6+$I6+$J6 -> -68 | L6: =Hypothèses!$B$36+$D6+$K6 -> -68 | M6: =SUMPRODUCT((Contrats!$C$6:$C$13="helpdesk")*($A6>=Contrats!$B$6:$B$13+Hypothèses!$B$23)*Contrats!$D$6:$D$13) -> 0 | N6: =SUMPRODUCT((Contrats!$C$6:$C$13="support")*($A6>=Contrats!$B$6:$B$13+Hypothèses!$B$23)*Contrats!$D$6:$D$13) -> 0
A7: 2 | B7: =$M7+$N7 -> 0 | C7: =IF($B7<=Hypothèses!$B$17,0,IF($M7=0,0,CEILING($M7/Hypothèses!$B$16,1))+IF($N7=0,0,CEILING($N7/Hypothèses!$B$16,1))) -> 0 | D7: =SUMPRODUCT((Contrats!$B$6:$B$13=$A7)*Contrats!$I$6:$I$13) -> 0 | E7: =SUMPRODUCT((Contrats!$B$6:$B$13=$A7)*Contrats!$J$6:$J$13) -> 0 | F7: =SUMPRODUCT(($A7>=Contrats!$B$6:$B$13+Hypothèses!$B$24)*Contrats!$G$6:$G$13)-SUMPRODUCT(($A7-Contrats!$B$6:$B$13-Hypothèses!$B$24>=0)*($A7-Contrats!$B$6:$B$13-Hypothèses!$B$24<Hypothèses!$B$29)*Contrats!$K$6:$K$13) -> 0 | G7: =(SUMPRODUCT(($A7>=Contrats!$B$6:$B$13+Hypothèses!$B$24+Hypothèses!$B$26)*Contrats!$G$6:$G$13)-SUMPRODUCT(($A7-Hypothèses!$B$26-Contrats!$B$6:$B$13-Hypothèses!$B$24>=0)*($A7-Hypothèses!$B$26-Contrats!$B$6:$B$13-Hypothèses!$B$24<Hypothèses!$B$29)*Contrats!$K$6:$K$13))*(1-Hypothèses!$B$33) -> 0 | H7: =-($B7*Hypothèses!$B$14+$C7*Hypothèses!$B$15) -> 0 | I7: =-SUMPRODUCT((Contrats!$B$6:$B$13=$A7)*Contrats!$H$6:$H$13)-SUMPRODUCT((Contrats!$B$6:$B$13=$A7)*Contrats!$L$6:$L$13)-IF(AND($B7>0,COUNTIF($B$6:$B7,">0")=1),Hypothèses!$B$42,0) -> 0 | J7: =-(Hypothèses!$B$19+Hypothèses!$B$20+IF($B7>0,Hypothèses!$B$40,0)+$G7*(Hypothèses!$B$34+Hypothèses!$B$43)) -> -68 | K7: =$G7+$E7+$H7+$I7+$J7 -> -68 | L7: =L6+$D7+$K7 -> -136 | M7: =SUMPRODUCT((Contrats!$C$6:$C$13="helpdesk")*($A7>=Contrats!$B$6:$B$13+Hypothèses!$B$23)*Contrats!$D$6:$D$13) -> 0 | N7: =SUMPRODUCT((Contrats!$C$6:$C$13="support")*($A7>=Contrats!$B$6:$B$13+Hypothèses!$B$23)*Contrats!$D$6:$D$13) -> 0
A8: 3 | B8: =$M8+$N8 -> 0 | C8: =IF($B8<=Hypothèses!$B$17,0,IF($M8=0,0,CEILING($M8/Hypothèses!$B$16,1))+IF($N8=0,0,CEILING($N8/Hypothèses!$B$16,1))) -> 0 | D8: =SUMPRODUCT((Contrats!$B$6:$B$13=$A8)*Contrats!$I$6:$I$13) -> 0 | E8: =SUMPRODUCT((Contrats!$B$6:$B$13=$A8)*Contrats!$J$6:$J$13) -> 0 | F8: =SUMPRODUCT(($A8>=Contrats!$B$6:$B$13+Hypothèses!$B$24)*Contrats!$G$6:$G$13)-SUMPRODUCT(($A8-Contrats!$B$6:$B$13-Hypothèses!$B$24>=0)*($A8-Contrats!$B$6:$B$13-Hypothèses!$B$24<Hypothèses!$B$29)*Contrats!$K$6:$K$13) -> 0 | G8: =(SUMPRODUCT(($A8>=Contrats!$B$6:$B$13+Hypothèses!$B$24+Hypothèses!$B$26)*Contrats!$G$6:$G$13)-SUMPRODUCT(($A8-Hypothèses!$B$26-Contrats!$B$6:$B$13-Hypothèses!$B$24>=0)*($A8-Hypothèses!$B$26-Contrats!$B$6:$B$13-Hypothèses!$B$24<Hypothèses!$B$29)*Contrats!$K$6:$K$13))*(1-Hypothèses!$B$33) -> 0 | H8: =-($B8*Hypothèses!$B$14+$C8*Hypothèses!$B$15) -> 0 | I8: =-SUMPRODUCT((Contrats!$B$6:$B$13=$A8)*Contrats!$H$6:$H$13)-SUMPRODUCT((Contrats!$B$6:$B$13=$A8)*Contrats!$L$6:$L$13)-IF(AND($B8>0,COUNTIF($B$6:$B8,">0")=1),Hypothèses!$B$42,0) -> 0 | J8: =-(Hypothèses!$B$19+Hypothèses!$B$20+IF($B8>0,Hypothèses!$B$40,0)+$G8*(Hypothèses!$B$34+Hypothèses!$B$43)) -> -68 | K8: =$G8+$E8+$H8+$I8+$J8 -> -68 | L8: =L7+$D8+$K8 -> -204 | M8: =SUMPRODUCT((Contrats!$C$6:$C$13="helpdesk")*($A8>=Contrats!$B$6:$B$13+Hypothèses!$B$23)*Contrats!$D$6:$D$13) -> 0 | N8: =SUMPRODUCT((Contrats!$C$6:$C$13="support")*($A8>=Contrats!$B$6:$B$13+Hypothèses!$B$23)*Contrats!$D$6:$D$13) -> 0
A9: 4 | B9: =$M9+$N9 -> 0 | C9: =IF($B9<=Hypothèses!$B$17,0,IF($M9=0,0,CEILING($M9/Hypothèses!$B$16,1))+IF($N9=0,0,CEILING($N9/Hypothèses!$B$16,1))) -> 0 | D9: =SUMPRODUCT((Contrats!$B$6:$B$13=$A9)*Contrats!$I$6:$I$13) -> 0 | E9: =SUMPRODUCT((Contrats!$B$6:$B$13=$A9)*Contrats!$J$6:$J$13) -> 2450 | F9: =SUMPRODUCT(($A9>=Contrats!$B$6:$B$13+Hypothèses!$B$24)*Contrats!$G$6:$G$13)-SUMPRODUCT(($A9-Contrats!$B$6:$B$13-Hypothèses!$B$24>=0)*($A9-Contrats!$B$6:$B$13-Hypothèses!$B$24<Hypothèses!$B$29)*Contrats!$K$6:$K$13) -> 0 | G9: =(SUMPRODUCT(($A9>=Contrats!$B$6:$B$13+Hypothèses!$B$24+Hypothèses!$B$26)*Contrats!$G$6:$G$13)-SUMPRODUCT(($A9-Hypothèses!$B$26-Contrats!$B$6:$B$13-Hypothèses!$B$24>=0)*($A9-Hypothèses!$B$26-Contrats!$B$6:$B$13-Hypothèses!$B$24<Hypothèses!$B$29)*Contrats!$K$6:$K$13))*(1-Hypothèses!$B$33) -> 0 | H9: =-($B9*Hypothèses!$B$14+$C9*Hypothèses!$B$15) -> 0 | I9: =-SUMPRODUCT((Contrats!$B$6:$B$13=$A9)*Contrats!$H$6:$H$13)-SUMPRODUCT((Contrats!$B$6:$B$13=$A9)*Contrats!$L$6:$L$13)-IF(AND($B9>0,COUNTIF($B$6:$B9,">0")=1),Hypothèses!$B$42,0) -> -6800 | J9: =-(Hypothèses!$B$19+Hypothèses!$B$20+IF($B9>0,Hypothèses!$B$40,0)+$G9*(Hypothèses!$B$34+Hypothèses!$B$43)) -> -68 | K9: =$G9+$E9+$H9+$I9+$J9 -> -4418 | L9: =L8+$D9+$K9 -> -4622 | M9: =SUMPRODUCT((Contrats!$C$6:$C$13="helpdesk")*($A9>=Contrats!$B$6:$B$13+Hypothèses!$B$23)*Contrats!$D$6:$D$13) -> 0 | N9: =SUMPRODUCT((Contrats!$C$6:$C$13="support")*($A9>=Contrats!$B$6:$B$13+Hypothèses!$B$23)*Contrats!$D$6:$D$13) -> 0
A10: 5 | B10: =$M10+$N10 -> 5 | C10: =IF($B10<=Hypothèses!$B$17,0,IF($M10=0,0,CEILING($M10/Hypothèses!$B$16,1))+IF($N10=0,0,CEILING($N10/Hypothèses!$B$16,1))) -> 0 | D10: =SUMPRODUCT((Contrats!$B$6:$B$13=$A10)*Contrats!$I$6:$I$13) -> 0 | E10: =SUMPRODUCT((Contrats!$B$6:$B$13=$A10)*Contrats!$J$6:$J$13) -> 0 | F10: =SUMPRODUCT(($A10>=Contrats!$B$6:$B$13+Hypothèses!$B$24)*Contrats!$G$6:$G$13)-SUMPRODUCT(($A10-Contrats!$B$6:$B$13-Hypothèses!$B$24>=0)*($A10-Contrats!$B$6:$B$13-Hypothèses!$B$24<Hypothèses!$B$29)*Contrats!$K$6:$K$13) -> 0 | G10: =(SUMPRODUCT(($A10>=Contrats!$B$6:$B$13+Hypothèses!$B$24+Hypothèses!$B$26)*Contrats!$G$6:$G$13)-SUMPRODUCT(($A10-Hypothèses!$B$26-Contrats!$B$6:$B$13-Hypothèses!$B$24>=0)*($A10-Hypothèses!$B$26-Contrats!$B$6:$B$13-Hypothèses!$B$24<Hypothèses!$B$29)*Contrats!$K$6:$K$13))*(1-Hypothèses!$B$33) -> 0 | H10: =-($B10*Hypothèses!$B$14+$C10*Hypothèses!$B$15) -> -3650 | I10: =-SUMPRODUCT((Contrats!$B$6:$B$13=$A10)*Contrats!$H$6:$H$13)-SUMPRODUCT((Contrats!$B$6:$B$13=$A10)*Contrats!$L$6:$L$13)-IF(AND($B10>0,COUNTIF($B$6:$B10,">0")=1),Hypothèses!$B$42,0) -> -450 | J10: =-(Hypothèses!$B$19+Hypothèses!$B$20+IF($B10>0,Hypothèses!$B$40,0)+$G10*(Hypothèses!$B$34+Hypothèses!$B$43)) -> -2288 | K10: =$G10+$E10+$H10+$I10+$J10 -> -6388 | L10: =L9+$D10+$K10 -> -11010 | M10: =SUMPRODUCT((Contrats!$C$6:$C$13="helpdesk")*($A10>=Contrats!$B$6:$B$13+Hypothèses!$B$23)*Contrats!$D$6:$D$13) -> 5 | N10: =SUMPRODUCT((Contrats!$C$6:$C$13="support")*($A10>=Contrats!$B$6:$B$13+Hypothèses!$B$23)*Contrats!$D$6:$D$13) -> 0
A11: 6 | B11: =$M11+$N11 -> 5 | C11: =IF($B11<=Hypothèses!$B$17,0,IF($M11=0,0,CEILING($M11/Hypothèses!$B$16,1))+IF($N11=0,0,CEILING($N11/Hypothèses!$B$16,1))) -> 0 | D11: =SUMPRODUCT((Contrats!$B$6:$B$13=$A11)*Contrats!$I$6:$I$13) -> 0 | E11: =SUMPRODUCT((Contrats!$B$6:$B$13=$A11)*Contrats!$J$6:$J$13) -> 0 | F11: =SUMPRODUCT(($A11>=Contrats!$B$6:$B$13+Hypothèses!$B$24)*Contrats!$G$6:$G$13)-SUMPRODUCT(($A11-Contrats!$B$6:$B$13-Hypothèses!$B$24>=0)*($A11-Contrats!$B$6:$B$13-Hypothèses!$B$24<Hypothèses!$B$29)*Contrats!$K$6:$K$13) -> 10000 | G11: =(SUMPRODUCT(($A11>=Contrats!$B$6:$B$13+Hypothèses!$B$24+Hypothèses!$B$26)*Contrats!$G$6:$G$13)-SUMPRODUCT(($A11-Hypothèses!$B$26-Contrats!$B$6:$B$13-Hypothèses!$B$24>=0)*($A11-Hypothèses!$B$26-Contrats!$B$6:$B$13-Hypothèses!$B$24<Hypothèses!$B$29)*Contrats!$K$6:$K$13))*(1-Hypothèses!$B$33) -> 0 | H11: =-($B11*Hypothèses!$B$14+$C11*Hypothèses!$B$15) -> -3650 | I11: =-SUMPRODUCT((Contrats!$B$6:$B$13=$A11)*Contrats!$H$6:$H$13)-SUMPRODUCT((Contrats!$B$6:$B$13=$A11)*Contrats!$L$6:$L$13)-IF(AND($B11>0,COUNTIF($B$6:$B11,">0")=1),Hypothèses!$B$42,0) -> 0 | J11: =-(Hypothèses!$B$19+Hypothèses!$B$20+IF($B11>0,Hypothèses!$B$40,0)+$G11*(Hypothèses!$B$34+Hypothèses!$B$43)) -> -2288 | K11: =$G11+$E11+$H11+$I11+$J11 -> -5938 | L11: =L10+$D11+$K11 -> -16948 | M11: =SUMPRODUCT((Contrats!$C$6:$C$13="helpdesk")*($A11>=Contrats!$B$6:$B$13+Hypothèses!$B$23)*Contrats!$D$6:$D$13) -> 5 | N11: =SUMPRODUCT((Contrats!$C$6:$C$13="support")*($A11>=Contrats!$B$6:$B$13+Hypothèses!$B$23)*Contrats!$D$6:$D$13) -> 0
A12: 7 | B12: =$M12+$N12 -> 5 | C12: =IF($B12<=Hypothèses!$B$17,0,IF($M12=0,0,CEILING($M12/Hypothèses!$B$16,1))+IF($N12=0,0,CEILING($N12/Hypothèses!$B$16,1))) -> 0 | D12: =SUMPRODUCT((Contrats!$B$6:$B$13=$A12)*Contrats!$I$6:$I$13) -> 0 | E12: =SUMPRODUCT((Contrats!$B$6:$B$13=$A12)*Contrats!$J$6:$J$13) -> 0 | F12: =SUMPRODUCT(($A12>=Contrats!$B$6:$B$13+Hypothèses!$B$24)*Contrats!$G$6:$G$13)-SUMPRODUCT(($A12-Contrats!$B$6:$B$13-Hypothèses!$B$24>=0)*($A12-Contrats!$B$6:$B$13-Hypothèses!$B$24<Hypothèses!$B$29)*Contrats!$K$6:$K$13) -> 10000 | G12: =(SUMPRODUCT(($A12>=Contrats!$B$6:$B$13+Hypothèses!$B$24+Hypothèses!$B$26)*Contrats!$G$6:$G$13)-SUMPRODUCT(($A12-Hypothèses!$B$26-Contrats!$B$6:$B$13-Hypothèses!$B$24>=0)*($A12-Hypothèses!$B$26-Contrats!$B$6:$B$13-Hypothèses!$B$24<Hypothèses!$B$29)*Contrats!$K$6:$K$13))*(1-Hypothèses!$B$33) -> 10000 | H12: =-($B12*Hypothèses!$B$14+$C12*Hypothèses!$B$15) -> -3650 | I12: =-SUMPRODUCT((Contrats!$B$6:$B$13=$A12)*Contrats!$H$6:$H$13)-SUMPRODUCT((Contrats!$B$6:$B$13=$A12)*Contrats!$L$6:$L$13)-IF(AND($B12>0,COUNTIF($B$6:$B12,">0")=1),Hypothèses!$B$42,0) -> 0 | J12: =-(Hypothèses!$B$19+Hypothèses!$B$20+IF($B12>0,Hypothèses!$B$40,0)+$G12*(Hypothèses!$B$34+Hypothèses!$B$43)) -> -2588 | K12: =$G12+$E12+$H12+$I12+$J12 -> 3762 | L12: =L11+$D12+$K12 -> -13186 | M12: =SUMPRODUCT((Contrats!$C$6:$C$13="helpdesk")*($A12>=Contrats!$B$6:$B$13+Hypothèses!$B$23)*Contrats!$D$6:$D$13) -> 5 | N12: =SUMPRODUCT((Contrats!$C$6:$C$13="support")*($A12>=Contrats!$B$6:$B$13+Hypothèses!$B$23)*Contrats!$D$6:$D$13) -> 0
A13: 8 | B13: =$M13+$N13 -> 5 | C13: =IF($B13<=Hypothèses!$B$17,0,IF($M13=0,0,CEILING($M13/Hypothèses!$B$16,1))+IF($N13=0,0,CEILING($N13/Hypothèses!$B$16,1))) -> 0 | D13: =SUMPRODUCT((Contrats!$B$6:$B$13=$A13)*Contrats!$I$6:$I$13) -> 0 | E13: =SUMPRODUCT((Contrats!$B$6:$B$13=$A13)*Contrats!$J$6:$J$13) -> 0 | F13: =SUMPRODUCT(($A13>=Contrats!$B$6:$B$13+Hypothèses!$B$24)*Contrats!$G$6:$G$13)-SUMPRODUCT(($A13-Contrats!$B$6:$B$13-Hypothèses!$B$24>=0)*($A13-Contrats!$B$6:$B$13-Hypothèses!$B$24<Hypothèses!$B$29)*Contrats!$K$6:$K$13) -> 10000 | G13: =(SUMPRODUCT(($A13>=Contrats!$B$6:$B$13+Hypothèses!$B$24+Hypothèses!$B$26)*Contrats!$G$6:$G$13)-SUMPRODUCT(($A13-Hypothèses!$B$26-Contrats!$B$6:$B$13-Hypothèses!$B$24>=0)*($A13-Hypothèses!$B$26-Contrats!$B$6:$B$13-Hypothèses!$B$24<Hypothèses!$B$29)*Contrats!$K$6:$K$13))*(1-Hypothèses!$B$33) -> 10000 | H13: =-($B13*Hypothèses!$B$14+$C13*Hypothèses!$B$15) -> -3650 | I13: =-SUMPRODUCT((Contrats!$B$6:$B$13=$A13)*Contrats!$H$6:$H$13)-SUMPRODUCT((Contrats!$B$6:$B$13=$A13)*Contrats!$L$6:$L$13)-IF(AND($B13>0,COUNTIF($B$6:$B13,">0")=1),Hypothèses!$B$42,0) -> 0 | J13: =-(Hypothèses!$B$19+Hypothèses!$B$20+IF($B13>0,Hypothèses!$B$40,0)+$G13*(Hypothèses!$B$34+Hypothèses!$B$43)) -> -2588 | K13: =$G13+$E13+$H13+$I13+$J13 -> 3762 | L13: =L12+$D13+$K13 -> -9424 | M13: =SUMPRODUCT((Contrats!$C$6:$C$13="helpdesk")*($A13>=Contrats!$B$6:$B$13+Hypothèses!$B$23)*Contrats!$D$6:$D$13) -> 5 | N13: =SUMPRODUCT((Contrats!$C$6:$C$13="support")*($A13>=Contrats!$B$6:$B$13+Hypothèses!$B$23)*Contrats!$D$6:$D$13) -> 0
A14: 9 | B14: =$M14+$N14 -> 5 | C14: =IF($B14<=Hypothèses!$B$17,0,IF($M14=0,0,CEILING($M14/Hypothèses!$B$16,1))+IF($N14=0,0,CEILING($N14/Hypothèses!$B$16,1))) -> 0 | D14: =SUMPRODUCT((Contrats!$B$6:$B$13=$A14)*Contrats!$I$6:$I$13) -> 0 | E14: =SUMPRODUCT((Contrats!$B$6:$B$13=$A14)*Contrats!$J$6:$J$13) -> 0 | F14: =SUMPRODUCT(($A14>=Contrats!$B$6:$B$13+Hypothèses!$B$24)*Contrats!$G$6:$G$13)-SUMPRODUCT(($A14-Contrats!$B$6:$B$13-Hypothèses!$B$24>=0)*($A14-Contrats!$B$6:$B$13-Hypothèses!$B$24<Hypothèses!$B$29)*Contrats!$K$6:$K$13) -> 10000 | G14: =(SUMPRODUCT(($A14>=Contrats!$B$6:$B$13+Hypothèses!$B$24+Hypothèses!$B$26)*Contrats!$G$6:$G$13)-SUMPRODUCT(($A14-Hypothèses!$B$26-Contrats!$B$6:$B$13-Hypothèses!$B$24>=0)*($A14-Hypothèses!$B$26-Contrats!$B$6:$B$13-Hypothèses!$B$24<Hypothèses!$B$29)*Contrats!$K$6:$K$13))*(1-Hypothèses!$B$33) -> 10000 | H14: =-($B14*Hypothèses!$B$14+$C14*Hypothèses!$B$15) -> -3650 | I14: =-SUMPRODUCT((Contrats!$B$6:$B$13=$A14)*Contrats!$H$6:$H$13)-SUMPRODUCT((Contrats!$B$6:$B$13=$A14)*Contrats!$L$6:$L$13)-IF(AND($B14>0,COUNTIF($B$6:$B14,">0")=1),Hypothèses!$B$42,0) -> 0 | J14: =-(Hypothèses!$B$19+Hypothèses!$B$20+IF($B14>0,Hypothèses!$B$40,0)+$G14*(Hypothèses!$B$34+Hypothèses!$B$43)) -> -2588 | K14: =$G14+$E14+$H14+$I14+$J14 -> 3762 | L14: =L13+$D14+$K14 -> -5662 | M14: =SUMPRODUCT((Contrats!$C$6:$C$13="helpdesk")*($A14>=Contrats!$B$6:$B$13+Hypothèses!$B$23)*Contrats!$D$6:$D$13) -> 5 | N14: =SUMPRODUCT((Contrats!$C$6:$C$13="support")*($A14>=Contrats!$B$6:$B$13+Hypothèses!$B$23)*Contrats!$D$6:$D$13) -> 0
A15: 10 | B15: =$M15+$N15 -> 5 | C15: =IF($B15<=Hypothèses!$B$17,0,IF($M15=0,0,CEILING($M15/Hypothèses!$B$16,1))+IF($N15=0,0,CEILING($N15/Hypothèses!$B$16,1))) -> 0 | D15: =SUMPRODUCT((Contrats!$B$6:$B$13=$A15)*Contrats!$I$6:$I$13) -> 0 | E15: =SUMPRODUCT((Contrats!$B$6:$B$13=$A15)*Contrats!$J$6:$J$13) -> 0 | F15: =SUMPRODUCT(($A15>=Contrats!$B$6:$B$13+Hypothèses!$B$24)*Contrats!$G$6:$G$13)-SUMPRODUCT(($A15-Contrats!$B$6:$B$13-Hypothèses!$B$24>=0)*($A15-Contrats!$B$6:$B$13-Hypothèses!$B$24<Hypothèses!$B$29)*Contrats!$K$6:$K$13) -> 10000 | G15: =(SUMPRODUCT(($A15>=Contrats!$B$6:$B$13+Hypothèses!$B$24+Hypothèses!$B$26)*Contrats!$G$6:$G$13)-SUMPRODUCT(($A15-Hypothèses!$B$26-Contrats!$B$6:$B$13-Hypothèses!$B$24>=0)*($A15-Hypothèses!$B$26-Contrats!$B$6:$B$13-Hypothèses!$B$24<Hypothèses!$B$29)*Contrats!$K$6:$K$13))*(1-Hypothèses!$B$33) -> 10000 | H15: =-($B15*Hypothèses!$B$14+$C15*Hypothèses!$B$15) -> -3650 | I15: =-SUMPRODUCT((Contrats!$B$6:$B$13=$A15)*Contrats!$H$6:$H$13)-SUMPRODUCT((Contrats!$B$6:$B$13=$A15)*Contrats!$L$6:$L$13)-IF(AND($B15>0,COUNTIF($B$6:$B15,">0")=1),Hypothèses!$B$42,0) -> 0 | J15: =-(Hypothèses!$B$19+Hypothèses!$B$20+IF($B15>0,Hypothèses!$B$40,0)+$G15*(Hypothèses!$B$34+Hypothèses!$B$43)) -> -2588 | K15: =$G15+$E15+$H15+$I15+$J15 -> 3762 | L15: =L14+$D15+$K15 -> -1900 | M15: =SUMPRODUCT((Contrats!$C$6:$C$13="helpdesk")*($A15>=Contrats!$B$6:$B$13+Hypothèses!$B$23)*Contrats!$D$6:$D$13) -> 5 | N15: =SUMPRODUCT((Contrats!$C$6:$C$13="support")*($A15>=Contrats!$B$6:$B$13+Hypothèses!$B$23)*Contrats!$D$6:$D$13) -> 0
A16: 11 | B16: =$M16+$N16 -> 5 | C16: =IF($B16<=Hypothèses!$B$17,0,IF($M16=0,0,CEILING($M16/Hypothèses!$B$16,1))+IF($N16=0,0,CEILING($N16/Hypothèses!$B$16,1))) -> 0 | D16: =SUMPRODUCT((Contrats!$B$6:$B$13=$A16)*Contrats!$I$6:$I$13) -> 0 | E16: =SUMPRODUCT((Contrats!$B$6:$B$13=$A16)*Contrats!$J$6:$J$13) -> 0 | F16: =SUMPRODUCT(($A16>=Contrats!$B$6:$B$13+Hypothèses!$B$24)*Contrats!$G$6:$G$13)-SUMPRODUCT(($A16-Contrats!$B$6:$B$13-Hypothèses!$B$24>=0)*($A16-Contrats!$B$6:$B$13-Hypothèses!$B$24<Hypothèses!$B$29)*Contrats!$K$6:$K$13) -> 10000 | G16: =(SUMPRODUCT(($A16>=Contrats!$B$6:$B$13+Hypothèses!$B$24+Hypothèses!$B$26)*Contrats!$G$6:$G$13)-SUMPRODUCT(($A16-Hypothèses!$B$26-Contrats!$B$6:$B$13-Hypothèses!$B$24>=0)*($A16-Hypothèses!$B$26-Contrats!$B$6:$B$13-Hypothèses!$B$24<Hypothèses!$B$29)*Contrats!$K$6:$K$13))*(1-Hypothèses!$B$33) -> 10000 | H16: =-($B16*Hypothèses!$B$14+$C16*Hypothèses!$B$15) -> -3650 | I16: =-SUMPRODUCT((Contrats!$B$6:$B$13=$A16)*Contrats!$H$6:$H$13)-SUMPRODUCT((Contrats!$B$6:$B$13=$A16)*Contrats!$L$6:$L$13)-IF(AND($B16>0,COUNTIF($B$6:$B16,">0")=1),Hypothèses!$B$42,0) -> 0 | J16: =-(Hypothèses!$B$19+Hypothèses!$B$20+IF($B16>0,Hypothèses!$B$40,0)+$G16*(Hypothèses!$B$34+Hypothèses!$B$43)) -> -2588 | K16: =$G16+$E16+$H16+$I16+$J16 -> 3762 | L16: =L15+$D16+$K16 -> 1862 | M16: =SUMPRODUCT((Contrats!$C$6:$C$13="helpdesk")*($A16>=Contrats!$B$6:$B$13+Hypothèses!$B$23)*Contrats!$D$6:$D$13) -> 5 | N16: =SUMPRODUCT((Contrats!$C$6:$C$13="support")*($A16>=Contrats!$B$6:$B$13+Hypothèses!$B$23)*Contrats!$D$6:$D$13) -> 0
A17: 12 | B17: =$M17+$N17 -> 5 | C17: =IF($B17<=Hypothèses!$B$17,0,IF($M17=0,0,CEILING($M17/Hypothèses!$B$16,1))+IF($N17=0,0,CEILING($N17/Hypothèses!$B$16,1))) -> 0 | D17: =SUMPRODUCT((Contrats!$B$6:$B$13=$A17)*Contrats!$I$6:$I$13) -> 0 | E17: =SUMPRODUCT((Contrats!$B$6:$B$13=$A17)*Contrats!$J$6:$J$13) -> 0 | F17: =SUMPRODUCT(($A17>=Contrats!$B$6:$B$13+Hypothèses!$B$24)*Contrats!$G$6:$G$13)-SUMPRODUCT(($A17-Contrats!$B$6:$B$13-Hypothèses!$B$24>=0)*($A17-Contrats!$B$6:$B$13-Hypothèses!$B$24<Hypothèses!$B$29)*Contrats!$K$6:$K$13) -> 10000 | G17: =(SUMPRODUCT(($A17>=Contrats!$B$6:$B$13+Hypothèses!$B$24+Hypothèses!$B$26)*Contrats!$G$6:$G$13)-SUMPRODUCT(($A17-Hypothèses!$B$26-Contrats!$B$6:$B$13-Hypothèses!$B$24>=0)*($A17-Hypothèses!$B$26-Contrats!$B$6:$B$13-Hypothèses!$B$24<Hypothèses!$B$29)*Contrats!$K$6:$K$13))*(1-Hypothèses!$B$33) -> 10000 | H17: =-($B17*Hypothèses!$B$14+$C17*Hypothèses!$B$15) -> -3650 | I17: =-SUMPRODUCT((Contrats!$B$6:$B$13=$A17)*Contrats!$H$6:$H$13)-SUMPRODUCT((Contrats!$B$6:$B$13=$A17)*Contrats!$L$6:$L$13)-IF(AND($B17>0,COUNTIF($B$6:$B17,">0")=1),Hypothèses!$B$42,0) -> 0 | J17: =-(Hypothèses!$B$19+Hypothèses!$B$20+IF($B17>0,Hypothèses!$B$40,0)+$G17*(Hypothèses!$B$34+Hypothèses!$B$43)) -> -2588 | K17: =$G17+$E17+$H17+$I17+$J17 -> 3762 | L17: =L16+$D17+$K17 -> 5624 | M17: =SUMPRODUCT((Contrats!$C$6:$C$13="helpdesk")*($A17>=Contrats!$B$6:$B$13+Hypothèses!$B$23)*Contrats!$D$6:$D$13) -> 5 | N17: =SUMPRODUCT((Contrats!$C$6:$C$13="support")*($A17>=Contrats!$B$6:$B$13+Hypothèses!$B$23)*Contrats!$D$6:$D$13) -> 0
A18: 13 | B18: =$M18+$N18 -> 5 | C18: =IF($B18<=Hypothèses!$B$17,0,IF($M18=0,0,CEILING($M18/Hypothèses!$B$16,1))+IF($N18=0,0,CEILING($N18/Hypothèses!$B$16,1))) -> 0 | D18: =SUMPRODUCT((Contrats!$B$6:$B$13=$A18)*Contrats!$I$6:$I$13) -> 0 | E18: =SUMPRODUCT((Contrats!$B$6:$B$13=$A18)*Contrats!$J$6:$J$13) -> 0 | F18: =SUMPRODUCT(($A18>=Contrats!$B$6:$B$13+Hypothèses!$B$24)*Contrats!$G$6:$G$13)-SUMPRODUCT(($A18-Contrats!$B$6:$B$13-Hypothèses!$B$24>=0)*($A18-Contrats!$B$6:$B$13-Hypothèses!$B$24<Hypothèses!$B$29)*Contrats!$K$6:$K$13) -> 10000 | G18: =(SUMPRODUCT(($A18>=Contrats!$B$6:$B$13+Hypothèses!$B$24+Hypothèses!$B$26)*Contrats!$G$6:$G$13)-SUMPRODUCT(($A18-Hypothèses!$B$26-Contrats!$B$6:$B$13-Hypothèses!$B$24>=0)*($A18-Hypothèses!$B$26-Contrats!$B$6:$B$13-Hypothèses!$B$24<Hypothèses!$B$29)*Contrats!$K$6:$K$13))*(1-Hypothèses!$B$33) -> 10000 | H18: =-($B18*Hypothèses!$B$14+$C18*Hypothèses!$B$15) -> -3650 | I18: =-SUMPRODUCT((Contrats!$B$6:$B$13=$A18)*Contrats!$H$6:$H$13)-SUMPRODUCT((Contrats!$B$6:$B$13=$A18)*Contrats!$L$6:$L$13)-IF(AND($B18>0,COUNTIF($B$6:$B18,">0")=1),Hypothèses!$B$42,0) -> 0 | J18: =-(Hypothèses!$B$19+Hypothèses!$B$20+IF($B18>0,Hypothèses!$B$40,0)+$G18*(Hypothèses!$B$34+Hypothèses!$B$43)) -> -2588 | K18: =$G18+$E18+$H18+$I18+$J18 -> 3762 | L18: =L17+$D18+$K18 -> 9386 | M18: =SUMPRODUCT((Contrats!$C$6:$C$13="helpdesk")*($A18>=Contrats!$B$6:$B$13+Hypothèses!$B$23)*Contrats!$D$6:$D$13) -> 5 | N18: =SUMPRODUCT((Contrats!$C$6:$C$13="support")*($A18>=Contrats!$B$6:$B$13+Hypothèses!$B$23)*Contrats!$D$6:$D$13) -> 0
... A29: 24 | B29: =$M29+$N29 -> 5 | C29: =IF($B29<=Hypothèses!$B$17,0,IF($M29=0,0,CEILING($M29/Hypothèses!$B$16,1))+IF($N29=0,0,CEILING($N29/Hypothèses!$B$16,1))) -> 0 | D29: =SUMPRODUCT((Contrats!$B$6:$B$13=$A29)*Contrats!$I$6:$I$13) -> 0 | E29: =SUMPRODUCT((Contrats!$B$6:$B$13=$A29)*Contrats!$J$6:$J$13) -> 0 | F29: =SUMPRODUCT(($A29>=Contrats!$B$6:$B$13+Hypothèses!$B$24)*Contrats!$G$6:$G$13)-SUMPRODUCT(($A29-Contrats!$B$6:$B$13-Hypothèses!$B$24>=0)*($A29-Contrats!$B$6:$B$13-Hypothèses!$B$24<Hypothèses!$B$29)*Contrats!$K$6:$K$13) -> 10000 | G29: =(SUMPRODUCT(($A29>=Contrats!$B$6:$B$13+Hypothèses!$B$24+Hypothèses!$B$26)*Contrats!$G$6:$G$13)-SUMPRODUCT(($A29-Hypothèses!$B$26-Contrats!$B$6:$B$13-Hypothèses!$B$24>=0)*($A29-Hypothèses!$B$26-Contrats!$B$6:$B$13-Hypothèses!$B$24<Hypothèses!$B$29)*Contrats!$K$6:$K$13))*(1-Hypothèses!$B$33) -> 10000 | H29: =-($B29*Hypothèses!$B$14+$C29*Hypothèses!$B$15) -> -3650 | I29: =-SUMPRODUCT((Contrats!$B$6:$B$13=$A29)*Contrats!$H$6:$H$13)-SUMPRODUCT((Contrats!$B$6:$B$13=$A29)*Contrats!$L$6:$L$13)-IF(AND($B29>0,COUNTIF($B$6:$B29,">0")=1),Hypothèses!$B$42,0) -> 0 | J29: =-(Hypothèses!$B$19+Hypothèses!$B$20+IF($B29>0,Hypothèses!$B$40,0)+$G29*(Hypothèses!$B$34+Hypothèses!$B$43)) -> -2588 | K29: =$G29+$E29+$H29+$I29+$J29 -> 3762 | L29: =L28+$D29+$K29 -> 50768 | M29: =SUMPRODUCT((Contrats!$C$6:$C$13="helpdesk")*($A29>=Contrats!$B$6:$B$13+Hypothèses!$B$23)*Contrats!$D$6:$D$13) -> 5 | N29: =SUMPRODUCT((Contrats!$C$6:$C$13="support")*($A29>=Contrats!$B$6:$B$13+Hypothèses!$B$23)*Contrats!$D$6:$D$13) -> 0
A31: Personnel, onboarding, équipement, structure et réserves sont négatifs : ce sont des sorties. La structure ne se paie qu'avec du personnel en poste ; le groupe et l'UPS sortent une fois, au premier mois avec du personnel. Le « Résultat » compte les frais d'activation, qui sont acquis, mais pas le dépôt, qui n'est qu'une avance rendue par crédit de facture — le dépôt n'apparaît que dans le cash. Les colonnes M et N (positions par métier) sont masquées : elles servent au calcul du nombre de managers, qui n'est pas mutualisé entre métiers.

Sheet Contribution
C1: Contribution à régime plein
C2: Tous les contrats actifs, hors onboarding, équipement, dépôt et impayés.
A5: Contrat | B5: Positions | C5: CA mensuel | D5: Coût des agents | E5: Contribution avant supervision
A6: =IF(Contrats!$D6="","",IF(Contrats!$A6="",Contrats!$C6,Contrats!$A6)) -> Client A | B6: =IF(Contrats!$D6="","",Contrats!$D6) -> 3 | C6: =IF(Contrats!$D6="","",Contrats!$G6) -> 6000 | D6: =IF(Contrats!$D6="","",-Contrats!$D6*Hypothèses!$B$14) -> -2190 | E6: =IF(Contrats!$D6="","",$C6+$D6) -> 3810
A7: =IF(Contrats!$D7="","",IF(Contrats!$A7="",Contrats!$C7,Contrats!$A7)) -> Client B | B7: =IF(Contrats!$D7="","",Contrats!$D7) -> 2 | C7: =IF(Contrats!$D7="","",Contrats!$G7) -> 4000 | D7: =IF(Contrats!$D7="","",-Contrats!$D7*Hypothèses!$B$14) -> -1460 | E7: =IF(Contrats!$D7="","",$C7+$D7) -> 2540
A8: =IF(Contrats!$D8="","",IF(Contrats!$A8="",Contrats!$C8,Contrats!$A8)) | B8: =IF(Contrats!$D8="","",Contrats!$D8) | C8: =IF(Contrats!$D8="","",Contrats!$G8) | D8: =IF(Contrats!$D8="","",-Contrats!$D8*Hypothèses!$B$14) | E8: =IF(Contrats!$D8="","",$C8+$D8)
A9: =IF(Contrats!$D9="","",IF(Contrats!$A9="",Contrats!$C9,Contrats!$A9)) | B9: =IF(Contrats!$D9="","",Contrats!$D9) | C9: =IF(Contrats!$D9="","",Contrats!$G9) | D9: =IF(Contrats!$D9="","",-Contrats!$D9*Hypothèses!$B$14) | E9: =IF(Contrats!$D9="","",$C9+$D9)
A10: =IF(Contrats!$D10="","",IF(Contrats!$A10="",Contrats!$C10,Contrats!$A10)) | B10: =IF(Contrats!$D10="","",Contrats!$D10) | C10: =IF(Contrats!$D10="","",Contrats!$G10) | D10: =IF(Contrats!$D10="","",-Contrats!$D10*Hypothèses!$B$14) | E10: =IF(Contrats!$D10="","",$C10+$D10)
A11: =IF(Contrats!$D11="","",IF(Contrats!$A11="",Contrats!$C11,Contrats!$A11)) | B11: =IF(Contrats!$D11="","",Contrats!$D11) | C11: =IF(Contrats!$D11="","",Contrats!$G11) | D11: =IF(Contrats!$D11="","",-Contrats!$D11*Hypothèses!$B$14) | E11: =IF(Contrats!$D11="","",$C11+$D11)
A12: =IF(Contrats!$D12="","",IF(Contrats!$A12="",Contrats!$C12,Contrats!$A12)) | B12: =IF(Contrats!$D12="","",Contrats!$D12) | C12: =IF(Contrats!$D12="","",Contrats!$G12) | D12: =IF(Contrats!$D12="","",-Contrats!$D12*Hypothèses!$B$14) | E12: =IF(Contrats!$D12="","",$C12+$D12)
A13: =IF(Contrats!$D13="","",IF(Contrats!$A13="",Contrats!$C13,Contrats!$A13)) | B13: =IF(Contrats!$D13="","",Contrats!$D13) | C13: =IF(Contrats!$D13="","",Contrats!$G13) | D13: =IF(Contrats!$D13="","",-Contrats!$D13*Hypothèses!$B$14) | E13: =IF(Contrats!$D13="","",$C13+$D13)
A15: Total des contrats | B15: =SUM(B6:B13) -> 5 | C15: =SUM(C6:C13) -> 10000 | D15: =SUM(D6:D13) -> -3650 | E15: =SUM(E6:E13) -> 6350
A16: Réserves SLA, banque et change | E16: =-C15*(Hypothèses!$B$34+Hypothèses!$B$43) -> -300
A17: Supervision à régime plein | B17: =Flux!C29 -> 0 | E17: =-Flux!C29*Hypothèses!$B$15 -> 0
A18: Outils et charges supplémentaires | E18: =-(Hypothèses!$B$19+Hypothèses!$B$20) -> -68
A19: Structure du lancement | E19: =-IF(B15>0,Hypothèses!$B$40,0) -> -2220
A20: RÉSULTAT MENSUEL À RÉGIME PLEIN | E20: =E15+E16+E17+E18+E19 -> 3762
A22: La supervision est comptée globalement, au nombre de managers du dernier mois : elle n'est pas répartie par contrat, parce qu'un manager déclenché par un contrat sert aussi au suivant dans le même métier. C'est le même « résultat mensuel à régime plein » que la page projection-finances-salverys.html — CA moins réserves, agents, supervision, outils et structure.
